tm_data_types/__init__.py
tm_data_types/datum/__init__.py
tm_data_types/datum/data_types.py
tm_data_types/datum/datum.py
tm_data_types/datum/waveforms/__init__.py
tm_data_types/datum/waveforms/analog_waveform.py
tm_data_types/datum/waveforms/digital_waveform.py
tm_data_types/datum/waveforms/iq_waveform.py
tm_data_types/datum/waveforms/waveform.py
tm_data_types/files_and_formats/__init__.py
tm_data_types/files_and_formats/abstracted_file.py
tm_data_types/files_and_formats/csv/__init__.py
tm_data_types/files_and_formats/csv/csv.py
tm_data_types/files_and_formats/csv/data_formats/__init__.py
tm_data_types/files_and_formats/csv/data_formats/analog.py
tm_data_types/files_and_formats/csv/data_formats/digital.py
tm_data_types/files_and_formats/csv/data_formats/iq.py
tm_data_types/files_and_formats/mat/__init__.py
tm_data_types/files_and_formats/mat/data_formats/__init__.py
tm_data_types/files_and_formats/mat/data_formats/analog.py
tm_data_types/files_and_formats/mat/data_formats/digital.py
tm_data_types/files_and_formats/mat/data_formats/iq.py
tm_data_types/files_and_formats/mat/mat.py
tm_data_types/files_and_formats/wfm/__init__.py
tm_data_types/files_and_formats/wfm/data_formats/__init__.py
tm_data_types/files_and_formats/wfm/data_formats/analog.py
tm_data_types/files_and_formats/wfm/data_formats/digital.py
tm_data_types/files_and_formats/wfm/data_formats/iq.py
tm_data_types/files_and_formats/wfm/wfm.py
tm_data_types/files_and_formats/wfm/wfm_data_classes.py
tm_data_types/files_and_formats/wfm/wfm_format.py
tm_data_types/helpers/__init__.py
tm_data_types/helpers/byte_data_class.py
tm_data_types/helpers/byte_data_types.py
tm_data_types/helpers/class_lookup.py
tm_data_types/helpers/enums.py
tm_data_types/helpers/instrument_series.py
tm_data_types/io_factory_methods.py
tm_data_types-0.2.0.dist-info/LICENSE.md
tm_data_types-0.2.0.dist-info/METADATA
tm_data_types-0.2.0.dist-info/WHEEL
tm_data_types-0.2.0.dist-info/RECORD
