Metadata-Version: 2.3
Name: tm_data_types
Version: 0.2.0
Summary: Read and write common Test & Measurement data types.
License: Apache-2.0
Keywords: Tektronix,Test & Measurement
Author: Tektronix
Author-email: opensource@tektronix.com
Maintainer: Tektronix
Maintainer-email: opensource@tektronix.com
Requires-Python: >=3.9.2,<3.14
Classifier: Development Status :: 4 - Beta
Classifier: Intended Audience :: Developers
Classifier: Intended Audience :: Science/Research
Classifier: License :: OSI Approved :: Apache Software License
Classifier: Operating System :: OS Independent
Classifier: Programming Language :: Python :: 3
Classifier: Programming Language :: Python :: 3.10
Classifier: Programming Language :: Python :: 3.11
Classifier: Programming Language :: Python :: 3.12
Classifier: Programming Language :: Python :: 3.13
Classifier: Programming Language :: Python :: 3.9
Classifier: Topic :: Scientific/Engineering
Classifier: Topic :: Scientific/Engineering :: Interface Engine/Protocol Translator
Classifier: Topic :: System :: Hardware :: Hardware Drivers
Requires-Dist: bidict (>=0.23.1,<0.24.0)
Requires-Dist: numba (>=0.60.0,<0.61.0) ; python_version >= "3.9" and python_version < "3.13"
Requires-Dist: numba (>=0.61.0,<0.62.0) ; python_version >= "3.13"
Requires-Dist: numpy (>=1.24,<2.0) ; python_version >= "3.9" and python_version < "3.13"
Requires-Dist: numpy (>=2.1,<3.0) ; python_version >= "3.13"
Requires-Dist: pydantic (>=2.7.4,<3.0.0)
Requires-Dist: python-dateutil (>=2.8.2,<3.0.0)
Requires-Dist: scipy (>=1.14,<2.0) ; python_version >= "3.13"
Requires-Dist: scipy (>=1.9,<2.0) ; python_version >= "3.9" and python_version < "3.13"
Project-URL: Bug Tracker, https://github.com/tektronix/tm_data_types/issues
Project-URL: Changelog, https://github.com/tektronix/tm_data_types/blob/main/CHANGELOG.md
Project-URL: Documentation, https://tm-data-types.readthedocs.io
Project-URL: Homepage, https://pypi.org/project/tm_data_types/
Project-URL: Repository, https://github.com/tektronix/tm_data_types
